<Properties GitUserInfo="UsingGIT" StartupConfiguration="{F58678C9-F883-460F-A678-0CDECB8E973A}|Default">
  <MonoDevelop.Ide.Workbench>
    <Files>
      <File FileName="Notes/Models/Note.cs" Line="9" Column="43" />
      <File FileName="Notes/NoteEntryPage.xaml" Line="27" Column="1" />
      <File FileName="Notes/NoteEntryPage.xaml.cs" Line="19" Column="58" />
      <File FileName="Notes/NotesPage.xaml" Line="8" Column="49" />
      <File FileName="Notes/App.xaml.cs" Line="31" Column="1" />
      <File FileName="Notes/NotesPage.xaml.cs" Line="44" Column="16" />
    </Files>
    <Pads>
      <Pad Id="ProjectPad">
        <State name="__root__">
          <Node name="Notes" expanded="True">
            <Node name="Notes" expanded="True">
              <Node name="Models" expanded="True" />
              <Node name="App.xaml" expanded="True" />
              <Node name="NoteEntryPage.xaml" expanded="True" />
              <Node name="NotesPage.xaml" expanded="True">
                <Node name="NotesPage.xaml.cs" selected="True" />
              </Node>
            </Node>
          </Node>
        </State>
      </Pad>
    </Pads>
  </MonoDevelop.Ide.Workbench>
  <MonoDevelop.Ide.ItemProperties.Notes.Android AndroidDesignerPreferredTheme="Theme.AppCompat.Light.NoActionBar" PreferredExecutionTarget="Android.pixel_2_pie_9_0_-_api_28" />
  <MonoDevelop.Ide.ItemProperties.Notes.iOS PreferredExecutionTarget="MonoDevelop.IPhone.IPhoneSimulatorTarget.C8BC97FB-59DF-4B3B-8D18-8A86924B3589" />
  <MonoDevelop.Ide.DebuggingService.PinnedWatches />
  <MonoDevelop.Ide.Workspace ActiveConfiguration="Debug" />
  <MonoDevelop.Ide.DebuggingService.Breakpoints>
    <BreakpointStore />
  </MonoDevelop.Ide.DebuggingService.Breakpoints>
  <MultiItemStartupConfigurations />
</Properties>